croma/__init__.py
croma/croma.py
croma-0.0.2.dist-info/LICENSE
croma-0.0.2.dist-info/METADATA
croma-0.0.2.dist-info/WHEEL
croma-0.0.2.dist-info/top_level.txt
croma-0.0.2.dist-info/RECORD
